visceng/__init__.py
visceng/__main__.py
visceng/game.py
visceng/tile.py
visceng/ui.py
visceng-0.1.0.dist-info/LICENSE
visceng-0.1.0.dist-info/METADATA
visceng-0.1.0.dist-info/WHEEL
visceng-0.1.0.dist-info/top_level.txt
visceng-0.1.0.dist-info/RECORD
