Metadata-Version: 2.1
Name: visceng
Version: 0.1.0
Summary: A fast 2D game engine for Python focused on normal-mapped lighting, optimized rendering, a simple API, and easy modding.
Home-page: https://github.com/N3rdL0rd/visceng
Author: N3rdL0rd
Author-email: n3rdl0rd@proton.me
Classifier: Programming Language :: Python :: 3
Classifier: License :: OSI Approved :: MIT License
Classifier: Operating System :: OS Independent
Requires-Python: >=3.6
License-File: LICENSE
Requires-Dist: pyglet
Requires-Dist: pdoc3
Requires-Dist: black
Requires-Dist: pyinstaller
Requires-Dist: setuptools
Requires-Dist: wheel
Requires-Dist: twine
